Metadata-Version: 2.0
Name: social-auth-backend-csh
Version: 0.1
Summary: A Python Social Auth backend for Computer Science House
Home-page: http://pypi.python.org/pypi/social-auth-backend-csh
Author: Steven Mirabito
Author-email: smirabito@csh.rit.edu
License: MIT
Download-URL: https://github.com/ComputerScienceHouse/social-auth-backend-csh/archive/0.1.tar.gz
Keywords: social,auth,oidc,openid,openid connect,csh,computer science house
Platform: OS Independent
Classifier: Development Status :: 4 - Beta
Classifier: Environment :: Web Environment
Classifier: Intended Audience :: Developers
Classifier: License :: OSI Approved :: MIT License
Classifier: Operating System :: OS Independent
Classifier: Programming Language :: Python
Classifier: Programming Language :: Python :: 2.7
Classifier: Programming Language :: Python :: 3
Classifier: Topic :: Internet
Classifier: Topic :: Security
Classifier: Topic :: Software Development :: Libraries :: Python Modules
Requires-Dist: social-core
